fudstop3/__init__.py
fudstop3/apis/__init__.py
fudstop3/apis/all_helpers.py
fudstop3/apis/helpers.py
fudstop3/apis/blotter/__init__.py
fudstop3/apis/blotter/blotter_sdk.py
fudstop3/apis/blotter/models.py
fudstop3/apis/markets/__init__.py
fudstop3/apis/markets/webhook_dicts.py
fudstop3/apis/markets/list_sets/__init__.py
fudstop3/apis/markets/list_sets/dicts.py
fudstop3/apis/markets/list_sets/saved_tickers.py
fudstop3/apis/markets/list_sets/ticker_lists.py
fudstop3/apis/markets/list_sets/webhook_dicts.py
fudstop3/apis/polygonio/__init__.py
fudstop3/apis/polygonio/async_polygon_sdk.py
fudstop3/apis/polygonio/db_polygon.py
fudstop3/apis/polygonio/mapping.py
fudstop3/apis/polygonio/polygon_database.py
fudstop3/apis/polygonio/polygon_helpers.py
fudstop3/apis/polygonio/polygon_options.py
fudstop3/apis/polygonio/polygon_sync.py
fudstop3/apis/polygonio/technicals.py
fudstop3/apis/polygonio/models/__init__.py
fudstop3/apis/polygonio/models/aggregates.py
fudstop3/apis/polygonio/models/company_info.py
fudstop3/apis/polygonio/models/daily_open_close.py
fudstop3/apis/polygonio/models/gainers_losers.py
fudstop3/apis/polygonio/models/quotes.py
fudstop3/apis/polygonio/models/technicals.py
fudstop3/apis/polygonio/models/ticker_news.py
fudstop3/apis/polygonio/models/ticker_snapshot.py
fudstop3/apis/polygonio/models/trades.py
fudstop3/apis/polygonio/models/option_models/__init__.py
fudstop3/apis/polygonio/models/option_models/option_snapshot.py
fudstop3/apis/polygonio/models/option_models/universal_option.py
fudstop3/apis/polygonio/models/option_models/universal_snapshot.py
fudstop3/apis/webull/__init__ - Copy.py
fudstop3/apis/webull/__init__.py
fudstop3/apis/webull/database_manager.py
fudstop3/apis/webull/futures.py
fudstop3/apis/webull/get_volume_analysis.py
fudstop3/apis/webull/industry.py
fudstop3/apis/webull/modal.py
fudstop3/apis/webull/newmodels.py
fudstop3/apis/webull/opt_modal.py
fudstop3/apis/webull/option_data.py
fudstop3/apis/webull/options.py
fudstop3-0.1.0.dist-info/METADATA
fudstop3-0.1.0.dist-info/WHEEL
fudstop3-0.1.0.dist-info/top_level.txt
fudstop3-0.1.0.dist-info/RECORD
