Metadata-Version: 2.1
Name: fudstop3
Version: 0.1.0
Summary: An all-in-one market data API aggregator for analysis and real-time feeds.
Author: Chuck Dustin
Author-email: chuckdustin12@gmail.com
Classifier: Programming Language :: Python :: 3
Classifier: License :: OSI Approved :: MIT License
Classifier: Operating System :: OS Independent
Requires-Python: >=3.7
